MANIFEST.in
README.rst
setup.cfg
setup.py
Linqp.egg-info/PKG-INFO
Linqp.egg-info/SOURCES.txt
Linqp.egg-info/dependency_links.txt
Linqp.egg-info/not-zip-safe
Linqp.egg-info/top_level.txt
linqp/__init__.py
linqp/linqp.py
linqp/__pycache__/__init__.cpython-36.pyc
linqp/__pycache__/linqp.cpython-36.pyc