Metadata-Version: 1.0
Name: Linqp
Version: 1.0.1
Summary: Simple LINQ implementation for python.
Home-page: UNKNOWN
Author: Max Biloborodko
Author-email: f1ashhimself@gmail.net
License: UNKNOWN
Platform: UNKNOWN
